flask_terminal/__init__.py
flask_terminal/config/logger_config.py
flask_terminal/handlers/terminal_session_handler.py
flask_terminal/static/flask-terminal/js/terminal.js
flask_terminal/templates/flask-terminal/terminal.html
flask_terminal/terminal_blueprint.py
flask_terminal-0.2.1.dist-info/LICENSE.md
flask_terminal-0.2.1.dist-info/METADATA
flask_terminal-0.2.1.dist-info/WHEEL
flask_terminal-0.2.1.dist-info/RECORD
