Metadata-Version: 2.1
Name: flask-terminal
Version: 0.2.1
Summary: Browser based terminal for flask, use with hyper HYPER caution
Home-page: https://github.com/thevgergroup/flask-terminal
License: MIT
Keywords: flask,terminal,browser,shell
Author: patrick o'leary
Author-email: pjaol@pjaol.com
Requires-Python: >=3.9,<4.0
Classifier: Framework :: Flask
Classifier: License :: OSI Approved :: MIT License
Classifier: Programming Language :: Python :: 3
Classifier: Programming Language :: Python :: 3.9
Classifier: Programming Language :: Python :: 3.10
Classifier: Programming Language :: Python :: 3.11
Classifier: Programming Language :: Python :: 3.12
Classifier: Programming Language :: Unix Shell
Classifier: Topic :: Internet :: WWW/HTTP :: WSGI :: Application
Classifier: Topic :: System :: Shells
Classifier: Topic :: System :: Systems Administration
Requires-Dist: flask (>=3.0.2,<4.0.0)
Project-URL: Repository, https://github.com/thevgergroup/flask-terminal
